vribieregetscode/__init__.py
vribieregetscode/script.py
vribieregetscode-0.1.0.dist-info/entry_points.txt
vribieregetscode-0.1.0.dist-info/WHEEL
vribieregetscode-0.1.0.dist-info/METADATA
vribieregetscode-0.1.0.dist-info/RECORD
